odoo/addons/l10n_it_ddt_mrp_kit/README.rst
odoo/addons/l10n_it_ddt_mrp_kit/__init__.py
odoo/addons/l10n_it_ddt_mrp_kit/__manifest__.py
odoo/addons/l10n_it_ddt_mrp_kit/i18n/it.po
odoo/addons/l10n_it_ddt_mrp_kit/i18n/l10n_it_ddt_mrp_kit.pot
odoo/addons/l10n_it_ddt_mrp_kit/models/__init__.py
odoo/addons/l10n_it_ddt_mrp_kit/models/stock_picking_package_preparation.py
odoo/addons/l10n_it_ddt_mrp_kit/models/stock_picking_package_preparation_line.py
odoo/addons/l10n_it_ddt_mrp_kit/readme/CONTRIBUTORS.rst
odoo/addons/l10n_it_ddt_mrp_kit/readme/DESCRIPTION.rst
odoo/addons/l10n_it_ddt_mrp_kit/readme/USAGE.rst
odoo/addons/l10n_it_ddt_mrp_kit/static/description/icon.png
odoo/addons/l10n_it_ddt_mrp_kit/static/description/index.html
odoo/addons/l10n_it_ddt_mrp_kit/tests/__init__.py
odoo/addons/l10n_it_ddt_mrp_kit/tests/test_td_invoice_kit.py
odoo12_addon_l10n_it_ddt_mrp_kit-12.0.1.0.0.99.dev6.dist-info/METADATA
odoo12_addon_l10n_it_ddt_mrp_kit-12.0.1.0.0.99.dev6.dist-info/WHEEL
odoo12_addon_l10n_it_ddt_mrp_kit-12.0.1.0.0.99.dev6.dist-info/top_level.txt
odoo12_addon_l10n_it_ddt_mrp_kit-12.0.1.0.0.99.dev6.dist-info/RECORD
